pynput_robocorp/__init__.py
pynput_robocorp/_info.py
pynput_robocorp/_util/__init__.py
pynput_robocorp/_util/darwin.py
pynput_robocorp/_util/win32.py
pynput_robocorp/_util/win32_vks.py
pynput_robocorp/_util/xorg.py
pynput_robocorp/_util/xorg_keysyms.py
pynput_robocorp/keyboard/__init__.py
pynput_robocorp/keyboard/_base.py
pynput_robocorp/keyboard/_darwin.py
pynput_robocorp/keyboard/_dummy.py
pynput_robocorp/keyboard/_win32.py
pynput_robocorp/keyboard/_xorg.py
pynput_robocorp/mouse/__init__.py
pynput_robocorp/mouse/_base.py
pynput_robocorp/mouse/_darwin.py
pynput_robocorp/mouse/_dummy.py
pynput_robocorp/mouse/_win32.py
pynput_robocorp/mouse/_xorg.py
pynput_robocorp_fork-4.0.0.dist-info/COPYING
pynput_robocorp_fork-4.0.0.dist-info/COPYING.LGPL
pynput_robocorp_fork-4.0.0.dist-info/METADATA
pynput_robocorp_fork-4.0.0.dist-info/WHEEL
pynput_robocorp_fork-4.0.0.dist-info/top_level.txt
pynput_robocorp_fork-4.0.0.dist-info/zip-safe
pynput_robocorp_fork-4.0.0.dist-info/RECORD
