Metadata-Version: 2.1
Name: pynput-robocorp-fork
Version: 4.0.0
Summary: Monitor and control user input devices
Home-page: https://github.com/robocorp/pynput
Author: Moses Palmér
Author-email: moses.palmer@gmail.com
License: LGPLv3
Keywords: control mouse,mouse input,control keyboard,keyboard input
Platform: UNKNOWN
Classifier: Development Status :: 5 - Production/Stable
Classifier: Intended Audience :: Developers
Classifier: License :: OSI Approved :: GNU Lesser General Public License v3 (LGPLv3)
Classifier: Operating System :: MacOS :: MacOS X
Classifier: Operating System :: Microsoft :: Windows :: Windows NT/2000
Classifier: Operating System :: POSIX
Classifier: Programming Language :: Python
Classifier: Programming Language :: Python :: 2.7
Classifier: Programming Language :: Python :: 3.4
Classifier: Programming Language :: Python :: 3.5
Classifier: Programming Language :: Python :: 3.6
Classifier: Programming Language :: Python :: 3.7
Classifier: Programming Language :: Python :: 3.8
Classifier: Programming Language :: Python :: 3.9
Classifier: Topic :: Software Development :: Libraries :: Python Modules
Classifier: Topic :: System :: Monitoring
Requires-Dist: six
Requires-Dist: python-xlib (>=0.17) ; "linux" in sys_platform
Requires-Dist: enum34 ; python_version == "2.7"
Requires-Dist: pyobjc-framework-Quartz (<8.0,>=7.0) ; sys_platform == "darwin"
Requires-Dist: pyobjc-framework-Cocoa (<8.0,>=7.0) ; sys_platform == "darwin"
Requires-Dist: pyobjc-core (<8.0,>=7.0) ; sys_platform == "darwin"
